{"text": "dwie\u015bcie trzydzie\u015bci osiem szeroka jest dolina i wida\u0107 kraj w oddali he\u0142my o kamieniach oprawnych w z\u0142oto b\u0142yszcz\u0105 i tarcze i pancerze przerabiane i w\u0142\u00f3cznie i proporce wisz\u0105 u\u017cele\u015bc\u00f3wsurmy graj\u0105 a g\u0142osy ich s\u0105 bardzo jasne a ruch dzwoni g\u0142o\u015bno do ataku emir wo\u0142a swego brata kanabeja kr\u00f3la florydy ten dzier\u017cy\u0142 ziemi\u0119 a\u017c do walseury pokazuje mu chor\u0105gwie karolowe patrzcie t\u0119 zachwalon\u0105 pych\u0119 francjicesarz jedzie bardzo dumnie jedzie z ty\u0142u z owymi starcami kt\u00f3rzy na pancerzach roz\u0142o\u017cyli swoje brody tak bia\u0142e jak \u015bniegi na lodach ci b\u0119d\u0105 dobrze bili mieczem i kopi\u0105 b\u0119dziemy mieli bitw\u0119 tward\u0105 i zawzi\u0119t\u0105 nigdy nie widziano podobnejdaleko przed swoim wojskiem dalej ni\u017c na rzucenie lask\u0105 baligant jedzie na koniu krzyczy p\u00f3jd\u017acie poganie bo ja ruszam w drog\u0119 potrz\u0105sa w\u0142\u00f3czni\u0105 obr\u00f3ci\u0142 ostrze przeciw karolowii", "chunks": [{"text": "dwie\u015bcie", "timestamp": [0.42, 0.82]}, {"text": "trzydzie\u015bci", "timestamp": [0.92, 1.46]}, {"text": "osiem", "timestamp": [1.58, 1.94]}, {"text": "szeroka", "timestamp": [2.84, 3.2]}, {"text": "jest", "timestamp": [3.26, 3.48]}, {"text": "dolina", "timestamp": [3.6, 3.98]}, {"text": "i", "timestamp": [4.54, 4.56]}, {"text": "wida\u0107", "timestamp": [4.62, 4.86]}, {"text": "kraj", "timestamp": [4.98, 5.32]}, {"text": "w", "timestamp": [5.42, 5.44]}, {"text": "oddali", "timestamp": [5.56, 6.06]}, {"text": "he\u0142my", "timestamp": [6.86, 7.26]}, {"text": "o", "timestamp": [7.46, 7.48]}, {"text": "kamieniach", "timestamp": [7.58, 8.1]}, {"text": "oprawnych", "timestamp": [8.22, 8.84]}, {"text": "w", "timestamp": [8.92, 8.94]}, {"text": "z\u0142oto", "timestamp": [9.02, 9.4]}, {"text": "b\u0142yszcz\u0105", "timestamp": [9.54, 10.08]}, {"text": "i", "timestamp": [10.66, 10.7]}, {"text": "tarcze", "timestamp": [10.8, 11.3]}, {"text": "i", "timestamp": [11.76, 11.78]}, {"text": "pancerze", "timestamp": [11.86, 12.4]}, {"text": "przerabiane", "timestamp": [12.48, 13.16]}, {"text": "i", "timestamp": [13.62, 13.66]}, {"text": "w\u0142\u00f3cznie", "timestamp": [13.74, 14.26]}, {"text": "i", "timestamp": [14.76, 14.78]}, {"text": "proporce", "timestamp": [14.86, 15.4]}, {"text": "wisz\u0105", "timestamp": [15.5, 15.8]}, {"text": "u\u017cele\u015bc\u00f3wsurmy", "timestamp": [16.06, 17.84]}, {"text": "graj\u0105", "timestamp": [17.92, 18.28]}, {"text": "a", "timestamp": [18.8, 18.82]}, {"text": "g\u0142osy", "timestamp": [18.9, 19.3]}, {"text": "ich", "timestamp": [19.42, 19.56]}, {"text": "s\u0105", "timestamp": [19.64, 19.74]}, {"text": "bardzo", "timestamp": [19.88, 20.22]}, {"text": "jasne", "timestamp": [20.28, 20.72]}, {"text": "a", "timestamp": [21.28, 21.32]}, {"text": "ruch", "timestamp": [21.44, 21.7]}, {"text": "dzwoni", "timestamp": [21.98, 22.32]}, {"text": "g\u0142o\u015bno", "timestamp": [22.4, 22.9]}, {"text": "do", "timestamp": [22.98, 23.06]}, {"text": "ataku", "timestamp": [23.16, 23.6]}, {"text": "emir", "timestamp": [24.3, 24.62]}, {"text": "wo\u0142a", "timestamp": [24.74, 24.94]}, {"text": "swego", "timestamp": [25.02, 25.28]}, {"text": "brata", "timestamp": [25.34, 25.74]}, {"text": "kanabeja", "timestamp": [26.06, 26.66]}, {"text": "kr\u00f3la", "timestamp": [27.36, 27.72]}, {"text": "florydy", "timestamp": [27.82, 28.38]}, {"text": "ten", "timestamp": [29.12, 29.36]}, {"text": "dzier\u017cy\u0142", "timestamp": [29.5, 29.98]}, {"text": "ziemi\u0119", "timestamp": [30.1, 30.42]}, {"text": "a\u017c", "timestamp": [30.64, 30.82]}, {"text": "do", "timestamp": [30.94, 31.04]}, {"text": "walseury", "timestamp": [31.26, 31.98]}, {"text": "pokazuje", "timestamp": [32.78, 33.18]}, {"text": "mu", "timestamp": [33.22, 33.3]}, {"text": "chor\u0105gwie", "timestamp": [33.34, 33.82]}, {"text": "karolowe", "timestamp": [33.9, 34.54]}, {"text": "patrzcie", "timestamp": [35.48, 35.98]}, {"text": "t\u0119", "timestamp": [36.66, 36.76]}, {"text": "zachwalon\u0105", "timestamp": [36.96, 37.62]}, {"text": "pych\u0119", "timestamp": [37.82, 38.06]}, {"text": "francjicesarz", "timestamp": [38.16, 39.8]}, {"text": "jedzie", "timestamp": [39.86, 40.08]}, {"text": "bardzo", "timestamp": [40.14, 40.5]}, {"text": "dumnie", "timestamp": [40.56, 40.96]}, {"text": "jedzie", "timestamp": [41.62, 41.82]}, {"text": "z", "timestamp": [41.9, 41.92]}, {"text": "ty\u0142u", "timestamp": [42.04, 42.36]}, {"text": "z", "timestamp": [42.52, 42.54]}, {"text": "owymi", "timestamp": [42.68, 42.94]}, {"text": "starcami", "timestamp": [43.04, 43.78]}, {"text": "kt\u00f3rzy", "timestamp": [44.26, 44.58]}, {"text": "na", "timestamp": [44.66, 44.74]}, {"text": "pancerzach", "timestamp": [44.86, 45.56]}, {"text": "roz\u0142o\u017cyli", "timestamp": [45.94, 46.5]}, {"text": "swoje", "timestamp": [46.58, 46.86]}, {"text": "brody", "timestamp": [46.94, 47.38]}, {"text": "tak", "timestamp": [47.82, 48.02]}, {"text": "bia\u0142e", "timestamp": [48.12, 48.46]}, {"text": "jak", "timestamp": [48.56, 48.74]}, {"text": "\u015bniegi", "timestamp": [48.86, 49.24]}, {"text": "na", "timestamp": [49.32, 49.4]}, {"text": "lodach", "timestamp": [49.48, 49.86]}, {"text": "ci", "timestamp": [50.72, 50.82]}, {"text": "b\u0119d\u0105", "timestamp": [50.92, 51.2]}, {"text": "dobrze", "timestamp": [51.34, 51.66]}, {"text": "bili", "timestamp": [51.76, 51.98]}, {"text": "mieczem", "timestamp": [52.1, 52.48]}, {"text": "i", "timestamp": [52.68, 52.72]}, {"text": "kopi\u0105", "timestamp": [52.84, 53.18]}, {"text": "b\u0119dziemy", "timestamp": [54.04, 54.42]}, {"text": "mieli", "timestamp": [54.46, 54.64]}, {"text": "bitw\u0119", "timestamp": [54.72, 55.02]}, {"text": "tward\u0105", "timestamp": [55.1, 55.56]}, {"text": "i", "timestamp": [55.76, 55.8]}, {"text": "zawzi\u0119t\u0105", "timestamp": [55.84, 56.42]}, {"text": "nigdy", "timestamp": [57.18, 57.52]}, {"text": "nie", "timestamp": [57.58, 57.68]}, {"text": "widziano", "timestamp": [57.72, 58.08]}, {"text": "podobnejdaleko", "timestamp": [58.14, 60.2]}, {"text": "przed", "timestamp": [60.28, 60.48]}, {"text": "swoim", "timestamp": [60.56, 60.84]}, {"text": "wojskiem", "timestamp": [60.94, 61.42]}, {"text": "dalej", "timestamp": [61.94, 62.24]}, {"text": "ni\u017c", "timestamp": [62.36, 62.56]}, {"text": "na", "timestamp": [62.68, 62.78]}, {"text": "rzucenie", "timestamp": [62.88, 63.3]}, {"text": "lask\u0105", "timestamp": [63.38, 63.76]}, {"text": "baligant", "timestamp": [64.4, 64.94]}, {"text": "jedzie", "timestamp": [65.4, 65.64]}, {"text": "na", "timestamp": [65.68, 65.76]}, {"text": "koniu", "timestamp": [65.86, 66.16]}, {"text": "krzyczy", "timestamp": [66.92, 67.3]}, {"text": "p\u00f3jd\u017acie", "timestamp": [68.16, 68.74]}, {"text": "poganie", "timestamp": [68.82, 69.28]}, {"text": "bo", "timestamp": [69.76, 69.86]}, {"text": "ja", "timestamp": [69.96, 70.06]}, {"text": "ruszam", "timestamp": [70.24, 70.56]}, {"text": "w", "timestamp": [70.66, 70.68]}, {"text": "drog\u0119", "timestamp": [70.76, 71.12]}, {"text": "potrz\u0105sa", "timestamp": [71.88, 72.34]}, {"text": "w\u0142\u00f3czni\u0105", "timestamp": [72.4, 72.86]}, {"text": "obr\u00f3ci\u0142", "timestamp": [73.52, 73.98]}, {"text": "ostrze", "timestamp": [74.2, 74.7]}, {"text": "przeciw", "timestamp": [74.8, 75.22]}, {"text": "karolowii", "timestamp": [75.32, 75.96]}]}