{"text": "sto dwadzie\u015bcia trzy hrabia rolant trzyma sw\u00f3j miecz zakrwawiony pos\u0142ysza\u0142 dobrze \u017ce francuzi trac\u0105 ducha tak si\u0119 tym zafrasowa\u0142 \u017ce omal mu serce nie p\u0119knie rzek\u0142 do poganina niechaj b\u00f3g ze\u015ble na ciebie wszystkie nieszcz\u0119\u015bcia drogo ci sprzedam tego kt\u00f3rego\u015b zabi\u0142 spina konia kt\u00f3ry zwyci\u0119\u017cy oto si\u0119 zmagaj\u0105", "chunks": [{"text": "sto", "timestamp": [0.52, 0.68]}, {"text": "dwadzie\u015bcia", "timestamp": [0.76, 1.24]}, {"text": "trzy", "timestamp": [1.34, 1.58]}, {"text": "hrabia", "timestamp": [2.5, 2.78]}, {"text": "rolant", "timestamp": [2.88, 3.36]}, {"text": "trzyma", "timestamp": [3.72, 4.0]}, {"text": "sw\u00f3j", "timestamp": [4.1, 4.34]}, {"text": "miecz", "timestamp": [4.44, 4.78]}, {"text": "zakrwawiony", "timestamp": [5.02, 5.8]}, {"text": "pos\u0142ysza\u0142", "timestamp": [6.34, 6.8]}, {"text": "dobrze", "timestamp": [6.9, 7.3]}, {"text": "\u017ce", "timestamp": [7.7, 7.78]}, {"text": "francuzi", "timestamp": [7.88, 8.42]}, {"text": "trac\u0105", "timestamp": [8.54, 8.92]}, {"text": "ducha", "timestamp": [9.12, 9.42]}, {"text": "tak", "timestamp": [10.12, 10.26]}, {"text": "si\u0119", "timestamp": [10.3, 10.38]}, {"text": "tym", "timestamp": [10.44, 10.54]}, {"text": "zafrasowa\u0142", "timestamp": [10.6, 11.28]}, {"text": "\u017ce", "timestamp": [11.64, 11.72]}, {"text": "omal", "timestamp": [11.9, 12.16]}, {"text": "mu", "timestamp": [12.24, 12.32]}, {"text": "serce", "timestamp": [12.42, 12.78]}, {"text": "nie", "timestamp": [12.82, 12.9]}, {"text": "p\u0119knie", "timestamp": [12.98, 13.46]}, {"text": "rzek\u0142", "timestamp": [14.1, 14.42]}, {"text": "do", "timestamp": [14.54, 14.6]}, {"text": "poganina", "timestamp": [14.7, 15.24]}, {"text": "niechaj", "timestamp": [15.78, 16.04]}, {"text": "b\u00f3g", "timestamp": [16.14, 16.36]}, {"text": "ze\u015ble", "timestamp": [16.48, 16.92]}, {"text": "na", "timestamp": [17.0, 17.06]}, {"text": "ciebie", "timestamp": [17.12, 17.36]}, {"text": "wszystkie", "timestamp": [17.42, 17.86]}, {"text": "nieszcz\u0119\u015bcia", "timestamp": [17.9, 18.66]}, {"text": "drogo", "timestamp": [19.22, 19.6]}, {"text": "ci", "timestamp": [19.68, 19.76]}, {"text": "sprzedam", "timestamp": [19.88, 20.34]}, {"text": "tego", "timestamp": [20.48, 20.74]}, {"text": "kt\u00f3rego\u015b", "timestamp": [21.18, 21.6]}, {"text": "zabi\u0142", "timestamp": [21.7, 22.12]}, {"text": "spina", "timestamp": [22.88, 23.22]}, {"text": "konia", "timestamp": [23.32, 23.62]}, {"text": "kt\u00f3ry", "timestamp": [24.42, 24.7]}, {"text": "zwyci\u0119\u017cy", "timestamp": [24.76, 25.38]}, {"text": "oto", "timestamp": [26.12, 26.32]}, {"text": "si\u0119", "timestamp": [26.42, 26.52]}, {"text": "zmagaj\u0105", "timestamp": [26.62, 27.16]}]}