{"text": "sto osiemdziesi\u0105t dwacesarz rozbi\u0142 ob\u00f3z francuzi ssiadaj\u0105 z koni w pustej okolicy rozkulbaczaj\u0105 konie zdejmuj\u0105 im z\u0142ocone uzdy puszczaj\u0105 je na \u0142\u0105k\u0119 jest tam obfito\u015b\u0107 \u015bwie\u017cej trawy to wszystko co im da\u0107 mog\u0105 kto jest bardzo znu\u017cony \u015bpi na ziemi tej nocy nie rozstawiono stra\u017cy", "chunks": [{"text": "sto", "timestamp": [0.48, 0.64]}, {"text": "osiemdziesi\u0105t", "timestamp": [0.82, 1.46]}, {"text": "dwacesarz", "timestamp": [1.56, 3.38]}, {"text": "rozbi\u0142", "timestamp": [3.68, 4.1]}, {"text": "ob\u00f3z", "timestamp": [4.26, 4.64]}, {"text": "francuzi", "timestamp": [5.44, 6.02]}, {"text": "ssiadaj\u0105", "timestamp": [6.14, 6.58]}, {"text": "z", "timestamp": [6.72, 6.74]}, {"text": "koni", "timestamp": [6.82, 7.08]}, {"text": "w", "timestamp": [7.16, 7.18]}, {"text": "pustej", "timestamp": [7.3, 7.66]}, {"text": "okolicy", "timestamp": [7.78, 8.34]}, {"text": "rozkulbaczaj\u0105", "timestamp": [9.02, 9.78]}, {"text": "konie", "timestamp": [9.94, 10.26]}, {"text": "zdejmuj\u0105", "timestamp": [10.8, 11.24]}, {"text": "im", "timestamp": [11.44, 11.54]}, {"text": "z\u0142ocone", "timestamp": [11.64, 12.08]}, {"text": "uzdy", "timestamp": [12.22, 12.58]}, {"text": "puszczaj\u0105", "timestamp": [13.06, 13.56]}, {"text": "je", "timestamp": [13.68, 13.76]}, {"text": "na", "timestamp": [13.84, 13.92]}, {"text": "\u0142\u0105k\u0119", "timestamp": [13.98, 14.4]}, {"text": "jest", "timestamp": [15.1, 15.32]}, {"text": "tam", "timestamp": [15.42, 15.56]}, {"text": "obfito\u015b\u0107", "timestamp": [15.8, 16.48]}, {"text": "\u015bwie\u017cej", "timestamp": [16.66, 17.04]}, {"text": "trawy", "timestamp": [17.14, 17.56]}, {"text": "to", "timestamp": [18.2, 18.26]}, {"text": "wszystko", "timestamp": [18.34, 18.88]}, {"text": "co", "timestamp": [19.24, 19.32]}, {"text": "im", "timestamp": [19.44, 19.5]}, {"text": "da\u0107", "timestamp": [19.6, 19.8]}, {"text": "mog\u0105", "timestamp": [19.94, 20.2]}, {"text": "kto", "timestamp": [21.06, 21.2]}, {"text": "jest", "timestamp": [21.24, 21.4]}, {"text": "bardzo", "timestamp": [21.48, 21.82]}, {"text": "znu\u017cony", "timestamp": [21.92, 22.54]}, {"text": "\u015bpi", "timestamp": [22.66, 22.88]}, {"text": "na", "timestamp": [22.94, 23.04]}, {"text": "ziemi", "timestamp": [23.12, 23.44]}, {"text": "tej", "timestamp": [24.04, 24.18]}, {"text": "nocy", "timestamp": [24.28, 24.64]}, {"text": "nie", "timestamp": [25.22, 25.32]}, {"text": "rozstawiono", "timestamp": [25.36, 26.04]}, {"text": "stra\u017cy", "timestamp": [26.12, 26.62]}]}