{"text": "siedemdziesi\u0105t bratanek marsyla trzyma r\u0119kawice w gar\u015bci rzecze do kr\u00f3la dumne s\u0142owo mi\u0142y panie kr\u00f3lu uczyni\u0142e\u015b mi wielki dar owo wybierz mi dwunastu ze swoich baron\u00f3w z nimi b\u0119d\u0119 walczy\u0142 przeciw dwunastu paromwraz odpowiada falasron brat kr\u00f3la marsylami\u0142y bratanku p\u00f3jdziemy wraz obaj ty i ja i z pewno\u015bci\u0105 stoczymy te bitwe z tylnymi stra\u017cami wielkiej armii karola rzecz postanowiona wybijemy ich", "chunks": [{"text": "siedemdziesi\u0105t", "timestamp": [0.44, 1.32]}, {"text": "bratanek", "timestamp": [2.5, 2.94]}, {"text": "marsyla", "timestamp": [3.0, 3.52]}, {"text": "trzyma", "timestamp": [3.7, 4.08]}, {"text": "r\u0119kawice", "timestamp": [4.14, 4.66]}, {"text": "w", "timestamp": [4.7, 4.74]}, {"text": "gar\u015bci", "timestamp": [4.8, 5.32]}, {"text": "rzecze", "timestamp": [5.9, 6.14]}, {"text": "do", "timestamp": [6.18, 6.26]}, {"text": "kr\u00f3la", "timestamp": [6.34, 6.64]}, {"text": "dumne", "timestamp": [6.76, 7.06]}, {"text": "s\u0142owo", "timestamp": [7.16, 7.58]}, {"text": "mi\u0142y", "timestamp": [8.62, 8.92]}, {"text": "panie", "timestamp": [9.06, 9.32]}, {"text": "kr\u00f3lu", "timestamp": [9.4, 9.84]}, {"text": "uczyni\u0142e\u015b", "timestamp": [10.38, 10.88]}, {"text": "mi", "timestamp": [10.96, 11.04]}, {"text": "wielki", "timestamp": [11.14, 11.48]}, {"text": "dar", "timestamp": [11.54, 11.82]}, {"text": "owo", "timestamp": [12.46, 12.7]}, {"text": "wybierz", "timestamp": [12.84, 13.24]}, {"text": "mi", "timestamp": [13.3, 13.38]}, {"text": "dwunastu", "timestamp": [13.48, 14.12]}, {"text": "ze", "timestamp": [14.22, 14.3]}, {"text": "swoich", "timestamp": [14.36, 14.7]}, {"text": "baron\u00f3w", "timestamp": [14.78, 15.3]}, {"text": "z", "timestamp": [15.66, 15.68]}, {"text": "nimi", "timestamp": [15.76, 15.98]}, {"text": "b\u0119d\u0119", "timestamp": [16.02, 16.26]}, {"text": "walczy\u0142", "timestamp": [16.32, 16.78]}, {"text": "przeciw", "timestamp": [17.12, 17.42]}, {"text": "dwunastu", "timestamp": [17.5, 18.0]}, {"text": "paromwraz", "timestamp": [18.12, 19.96]}, {"text": "odpowiada", "timestamp": [20.18, 20.8]}, {"text": "falasron", "timestamp": [21.28, 22.02]}, {"text": "brat", "timestamp": [22.56, 22.9]}, {"text": "kr\u00f3la", "timestamp": [23.04, 23.44]}, {"text": "marsylami\u0142y", "timestamp": [23.52, 24.94]}, {"text": "bratanku", "timestamp": [25.0, 25.62]}, {"text": "p\u00f3jdziemy", "timestamp": [26.16, 26.58]}, {"text": "wraz", "timestamp": [26.64, 26.88]}, {"text": "obaj", "timestamp": [27.14, 27.46]}, {"text": "ty", "timestamp": [27.88, 27.98]}, {"text": "i", "timestamp": [28.26, 28.3]}, {"text": "ja", "timestamp": [28.4, 28.5]}, {"text": "i", "timestamp": [29.2, 29.24]}, {"text": "z", "timestamp": [29.26, 29.28]}, {"text": "pewno\u015bci\u0105", "timestamp": [29.36, 29.84]}, {"text": "stoczymy", "timestamp": [30.0, 30.5]}, {"text": "te", "timestamp": [30.56, 30.64]}, {"text": "bitwe", "timestamp": [30.72, 31.08]}, {"text": "z", "timestamp": [31.42, 31.44]}, {"text": "tylnymi", "timestamp": [31.52, 31.88]}, {"text": "stra\u017cami", "timestamp": [31.96, 32.56]}, {"text": "wielkiej", "timestamp": [32.64, 33.06]}, {"text": "armii", "timestamp": [33.22, 33.56]}, {"text": "karola", "timestamp": [33.62, 34.04]}, {"text": "rzecz", "timestamp": [34.66, 34.88]}, {"text": "postanowiona", "timestamp": [34.96, 35.72]}, {"text": "wybijemy", "timestamp": [36.28, 36.84]}, {"text": "ich", "timestamp": [36.96, 37.14]}]}