{"text": "jacek podsiad\u0142o nicze ha\u0144b\u0105 jest by\u0107 szcz\u0119\u015bliwymdogl\u0105dam mu mocniej trac\u0119 kontakt z rzeczywisto\u015bci\u0105 m\u00f3wi\u0119 nie wiem nie znam nie ogl\u0105dam nie s\u0142ucham jeszcze gazety nigdy nic nie zrobi\u0142em dla torturowanychjak\u017ce zazdroszcz\u0119 tym co nie wierz\u0105 w o \u015bwi\u0119ci w pi\u0119tna\u015bcie lat po hitlerze \u015bwiat podbi\u0142 rokendrol simon wail mia\u0142a mojej lata kiedy si\u0119 zag\u0142odzi\u0142ahistorie biologie nauki \u015bcis\u0142e wszystko u\u0142o\u017cyli\u015bmy sobie tak\u017ceby usprawiedliwia\u0142o orgazm ma\u0142a \u015bmier\u0107 a przyjemno\u015b\u0107 dura u\u015bmiech poha\u0144bienia na twarzy kobiety u\u015bmiech oprawce na twarzy ch\u0142opca lub odwrotnie czy warto rozdrapywa\u0107 rany a co zagoi\u0142y si\u0119odk\u0105d pami\u0119tam chcia\u0142em wyda\u0107 t\u0105 wierszy pod tytu\u0142em nie wi\u0119c si\u0119 umacniam tu po prawie zapa\u0142k\u0119 tam do \u0142o\u017cy ciermczyta\u0142 adam fidusiewicz wolne lektury p el zosta\u0144 naszym przyjacielem", "chunks": [{"text": "jacek", "timestamp": [0.06, 0.34]}, {"text": "podsiad\u0142o", "timestamp": [0.38, 0.84]}, {"text": "nicze", "timestamp": [2.02, 2.3]}, {"text": "ha\u0144b\u0105", "timestamp": [2.96, 3.26]}, {"text": "jest", "timestamp": [3.34, 3.46]}, {"text": "by\u0107", "timestamp": [3.52, 3.66]}, {"text": "szcz\u0119\u015bliwymdogl\u0105dam", "timestamp": [3.72, 6.94]}, {"text": "mu", "timestamp": [7.0, 7.04]}, {"text": "mocniej", "timestamp": [7.1, 7.46]}, {"text": "trac\u0119", "timestamp": [8.62, 8.88]}, {"text": "kontakt", "timestamp": [8.96, 9.3]}, {"text": "z", "timestamp": [9.34, 9.38]}, {"text": "rzeczywisto\u015bci\u0105", "timestamp": [9.42, 10.12]}, {"text": "m\u00f3wi\u0119", "timestamp": [10.64, 10.92]}, {"text": "nie", "timestamp": [11.18, 11.3]}, {"text": "wiem", "timestamp": [11.36, 11.56]}, {"text": "nie", "timestamp": [12.2, 12.3]}, {"text": "znam", "timestamp": [12.38, 12.64]}, {"text": "nie", "timestamp": [12.9, 13.02]}, {"text": "ogl\u0105dam", "timestamp": [13.08, 13.58]}, {"text": "nie", "timestamp": [13.64, 13.72]}, {"text": "s\u0142ucham", "timestamp": [13.78, 14.12]}, {"text": "jeszcze", "timestamp": [15.4, 15.6]}, {"text": "gazety", "timestamp": [15.66, 16.08]}, {"text": "nigdy", "timestamp": [17.9, 18.14]}, {"text": "nic", "timestamp": [18.2, 18.36]}, {"text": "nie", "timestamp": [18.4, 18.48]}, {"text": "zrobi\u0142em", "timestamp": [18.52, 18.86]}, {"text": "dla", "timestamp": [18.9, 18.98]}, {"text": "torturowanychjak\u017ce", "timestamp": [19.04, 21.64]}, {"text": "zazdroszcz\u0119", "timestamp": [21.68, 22.18]}, {"text": "tym", "timestamp": [22.26, 22.4]}, {"text": "co", "timestamp": [22.48, 22.56]}, {"text": "nie", "timestamp": [22.6, 22.7]}, {"text": "wierz\u0105", "timestamp": [22.76, 23.0]}, {"text": "w", "timestamp": [23.06, 23.08]}, {"text": "o", "timestamp": [23.12, 23.14]}, {"text": "\u015bwi\u0119ci", "timestamp": [23.2, 23.6]}, {"text": "w", "timestamp": [24.94, 24.98]}, {"text": "pi\u0119tna\u015bcie", "timestamp": [25.02, 25.48]}, {"text": "lat", "timestamp": [25.52, 25.66]}, {"text": "po", "timestamp": [25.72, 25.8]}, {"text": "hitlerze", "timestamp": [25.86, 26.24]}, {"text": "\u015bwiat", "timestamp": [26.36, 26.62]}, {"text": "podbi\u0142", "timestamp": [26.7, 27.02]}, {"text": "rokendrol", "timestamp": [27.08, 27.66]}, {"text": "simon", "timestamp": [29.06, 29.32]}, {"text": "wail", "timestamp": [29.42, 29.7]}, {"text": "mia\u0142a", "timestamp": [29.92, 30.1]}, {"text": "mojej", "timestamp": [30.14, 30.38]}, {"text": "lata", "timestamp": [30.42, 30.64]}, {"text": "kiedy", "timestamp": [30.7, 30.88]}, {"text": "si\u0119", "timestamp": [30.9, 30.98]}, {"text": "zag\u0142odzi\u0142ahistorie", "timestamp": [31.02, 34.2]}, {"text": "biologie", "timestamp": [34.86, 35.28]}, {"text": "nauki", "timestamp": [35.7, 36.0]}, {"text": "\u015bcis\u0142e", "timestamp": [36.1, 36.58]}, {"text": "wszystko", "timestamp": [37.92, 38.26]}, {"text": "u\u0142o\u017cyli\u015bmy", "timestamp": [38.34, 38.92]}, {"text": "sobie", "timestamp": [38.96, 39.16]}, {"text": "tak\u017ceby", "timestamp": [39.22, 39.6]}, {"text": "usprawiedliwia\u0142o", "timestamp": [39.7, 40.54]}, {"text": "orgazm", "timestamp": [41.94, 42.4]}, {"text": "ma\u0142a", "timestamp": [42.58, 42.78]}, {"text": "\u015bmier\u0107", "timestamp": [42.86, 43.24]}, {"text": "a", "timestamp": [43.88, 43.9]}, {"text": "przyjemno\u015b\u0107", "timestamp": [43.96, 44.48]}, {"text": "dura", "timestamp": [44.56, 44.8]}, {"text": "u\u015bmiech", "timestamp": [46.9, 47.16]}, {"text": "poha\u0144bienia", "timestamp": [47.22, 47.7]}, {"text": "na", "timestamp": [47.74, 47.8]}, {"text": "twarzy", "timestamp": [47.84, 48.1]}, {"text": "kobiety", "timestamp": [48.16, 48.54]}, {"text": "u\u015bmiech", "timestamp": [49.76, 50.0]}, {"text": "oprawce", "timestamp": [50.06, 50.5]}, {"text": "na", "timestamp": [50.56, 50.62]}, {"text": "twarzy", "timestamp": [50.68, 50.94]}, {"text": "ch\u0142opca", "timestamp": [50.96, 51.38]}, {"text": "lub", "timestamp": [51.56, 51.66]}, {"text": "odwrotnie", "timestamp": [51.7, 52.18]}, {"text": "czy", "timestamp": [53.94, 54.04]}, {"text": "warto", "timestamp": [54.1, 54.38]}, {"text": "rozdrapywa\u0107", "timestamp": [54.42, 55.0]}, {"text": "rany", "timestamp": [55.1, 55.36]}, {"text": "a", "timestamp": [56.68, 56.7]}, {"text": "co", "timestamp": [56.78, 56.9]}, {"text": "zagoi\u0142y", "timestamp": [57.06, 57.54]}, {"text": "si\u0119odk\u0105d", "timestamp": [57.64, 60.54]}, {"text": "pami\u0119tam", "timestamp": [60.6, 61.0]}, {"text": "chcia\u0142em", "timestamp": [61.04, 61.3]}, {"text": "wyda\u0107", "timestamp": [61.36, 61.62]}, {"text": "t\u0105", "timestamp": [61.72, 61.8]}, {"text": "wierszy", "timestamp": [61.94, 62.26]}, {"text": "pod", "timestamp": [62.34, 62.46]}, {"text": "tytu\u0142em", "timestamp": [62.56, 62.92]}, {"text": "nie", "timestamp": [63.22, 63.36]}, {"text": "wi\u0119c", "timestamp": [65.04, 65.18]}, {"text": "si\u0119", "timestamp": [65.24, 65.32]}, {"text": "umacniam", "timestamp": [65.38, 65.82]}, {"text": "tu", "timestamp": [67.1, 67.18]}, {"text": "po", "timestamp": [67.24, 67.32]}, {"text": "prawie", "timestamp": [67.38, 67.6]}, {"text": "zapa\u0142k\u0119", "timestamp": [67.64, 68.12]}, {"text": "tam", "timestamp": [69.4, 69.52]}, {"text": "do", "timestamp": [69.6, 69.66]}, {"text": "\u0142o\u017cy", "timestamp": [69.72, 69.96]}, {"text": "ciermczyta\u0142", "timestamp": [70.06, 73.02]}, {"text": "adam", "timestamp": [73.1, 73.32]}, {"text": "fidusiewicz", "timestamp": [73.38, 74.04]}, {"text": "wolne", "timestamp": [74.58, 74.8]}, {"text": "lektury", "timestamp": [74.84, 75.14]}, {"text": "p", "timestamp": [75.2, 75.22]}, {"text": "el", "timestamp": [75.36, 75.5]}, {"text": "zosta\u0144", "timestamp": [76.04, 76.32]}, {"text": "naszym", "timestamp": [76.36, 76.58]}, {"text": "przyjacielem", "timestamp": [76.62, 77.14]}]}