{"text": "pie\u015b\u0144 o mowie naszej rzecz a\u017c nazbyt oczywista \u017ce jest pi\u0119kn\u0105 polska mowa j\u0119drna pachn\u0105ca soczysta melodyjna kolorowa bohaterska gromow\u0142adna czysta niby b\u0142\u0119ki t nieba m\u0105dra zacna mi\u0142a \u0142adna ale czasem przyzna\u0107 trzeba \u017ce ten j\u0119zyk najobfitszy w poetyczne r\u00f3\u017cne kwiatki w uczu\u0107 sferze pospoliczej zdradza dziwne niedostatki \u017ce w podniebnej wysoko\u015bci nazbyt g\u00f3rnie toczy skrzyd\u0142a a nas ludzi z krwi i ko\u015bci poniewiera gorzej byd\u0142ato co ziemi\u0119 wrajnamzmienia \u017cycia ca\u0142y wdzi\u0119k stanowi na to nie ma wyra\u017cenia o tym w polsce si\u0119 nie m\u00f3wipytam tu obecne panie by od grubszych zacz\u0105\u0107 brak\u00f3w jak mam nazwa\u0107 obcowanie dwojga r\u00f3\u017cnej p\u0142ci polak\u00f3w czy du\u017c bratnich pokrewie\u0144stwem czy tarzaniem si\u0119 w rozpu\u015bcie serckomuni\u0105 czy te\u017c \u015bwi\u0144stwem lub czym innym w takim gu\u015bcie cudzo\u0142o\u017cy\u0107 jawno grzeszy\u0107 dalej ju\u017c po\u0142o\u017ce kreski reszt\u0105 mo\u017ce was ucieszy\u0107 juzef albin hrybaczewskicho\u0107 poezi \u015bwi\u0119ci wiosne wieszcz\u00f3w naszych dzielna tr\u00f3jka polskie s\u0142ownictwo mi\u0142osne przypomina ksi\u0119dza w\u00f3jkadowody najoczywistsze znajdziesz cho\u0107by w takim g\u0142upstwie \u017ce polskiego s\u0142owa mistrze \u015bni\u0105 o rui i por\u00f3bstwie w archaicznym tym zamencie jak ma kwitn\u0105\u0107 szcz\u0119\u015bcia era gdzie zatraca si\u0119 poj\u0119cie tam i sama rzecz umieraludziom trzeba tak niewiele by na ziemi niebo stworzy\u0107 lecz wykrztusi\u0107 jak aniele ja chce z tob\u0105 cudzo\u0142o\u017cy\u0107 jak wyszepta\u0107 do dziewcz\u0119cia chc\u0119 pozbawi\u0107 ci\u0119 dziewictwa nie obawiaj si\u0119 pocz\u0119cia kpij sobie z jawnogrzesznictwa jak kusi\u0107 g\u0142osem zdradzieckim wabi\u0107 s\u0142odkich zakl\u0119\u0107 gam\u0105 ka\u017cdy wyraz pachnie dzieckiem ka\u017cde s\u0142owo drzesie mamo nazbyt trudno w tym dialekcie romansowe snu\u0107 intrygi polak cnote ma w respekcie lub tentuje j\u0105 na migi st\u0105d gdy w polsce do kolacji p\u0142cie odmienne si\u0105d\u0105 spo\u0142em g\u0142\u00f3wna cz\u0105stka konwersacji zwyk\u0142a toczy\u0107 si\u0119 pod sto\u0142em niech upadnie ci serweta cz\u0142owiek oczom swym nie wierzy gdzie m\u0119\u017cczyzna gdzie kobieta kt\u00f3ranoga gdzie nale\u017cy pantofelk\u00f3w but\u00f3w g\u0119stwa fantastycznie popl\u0105tana stacza walki pe\u0142ne m\u0119stwa istny grunwald mistrza jana tak pod sto\u0142em wiecz\u00f3r ca\u0142y gimnastyczne trwa \u0107wiczenie na przy stole komuna\u0142y o\u017ce romskim lub ipsenie lecz najci\u0119\u017csz\u0105 budzi troske \u017ce marnieje lud nasz chwacki \u017ce ju\u017c cich\u0105 polsk\u0105 wiosk\u0119 skazi\u0142 \u017cargon literackinawie\u015b gdy si\u0119 cz\u0142ek dob\u0119dzie chc\u0105c odetchn\u0105\u0107 \u017cyciem zdrowszem s\u0142yszy ka\u015bka jak ze b\u0119dzie wzgl\u0119dem tego co i owszem widz\u0119 tu zebran\u0105 t\u0142umnie kap\u0142an\u00f3w sztuki elite co swe kud\u0142y wznosz\u0105 dumnie ponad rzesze pospolite wy \u015bwietlanych duch\u00f3w zwi\u0105zek w idei stru\u017ceczystej wasz to jest psi obowi\u0105zek kszta\u0142ci\u0107 j\u0119zyk ten ojczysty sko\u0144czcie wasze komedyje schowajcie pawie ogony \u017cyjcie czym ka\u017cdy z nas \u017cyje id\u017acie kocha\u0107 zamiliony do\u015b\u0107 nastroj\u00f3w waszych dranie uczcie m\u00f3wi\u0107 waszych braci to jest wasze powo\u0142anie od tego was nar\u00f3d p\u0142aci j\u0119zyk naszym skarbem \u015bwi\u0119tym niej graszk\u0105 oboj\u0119tn\u0105 nie krwi\u0105 ale atramentem bije dzisiaj lud\u00f3w t\u0119tnomusi naprz\u00f3d i\u015b\u0107 z \u017cywemi a nie t\u0119pi\u0107 \u017cycia zarut sok\u00f3w pe\u0142nie czerpa\u0107 z ziemi jaki j\u0119zyk taki nar\u00f3d pisane w roku tysi\u0105c dziewi\u0119\u0107set si\u00f3dmym", "chunks": [{"text": "pie\u015b\u0144", "timestamp": [0.36, 0.78]}, {"text": "o", "timestamp": [1.02, 1.04]}, {"text": "mowie", "timestamp": [1.18, 1.5]}, {"text": "naszej", "timestamp": [1.58, 2.02]}, {"text": "rzecz", "timestamp": [3.24, 3.52]}, {"text": "a\u017c", "timestamp": [3.78, 3.94]}, {"text": "nazbyt", "timestamp": [4.1, 4.46]}, {"text": "oczywista", "timestamp": [4.54, 5.12]}, {"text": "\u017ce", "timestamp": [5.62, 5.7]}, {"text": "jest", "timestamp": [5.74, 5.9]}, {"text": "pi\u0119kn\u0105", "timestamp": [6.02, 6.52]}, {"text": "polska", "timestamp": [6.8, 7.24]}, {"text": "mowa", "timestamp": [7.3, 7.58]}, {"text": "j\u0119drna", "timestamp": [8.14, 8.7]}, {"text": "pachn\u0105ca", "timestamp": [8.94, 9.62]}, {"text": "soczysta", "timestamp": [10.16, 10.72]}, {"text": "melodyjna", "timestamp": [11.28, 11.96]}, {"text": "kolorowa", "timestamp": [12.42, 13.0]}, {"text": "bohaterska", "timestamp": [13.52, 14.28]}, {"text": "gromow\u0142adna", "timestamp": [14.56, 15.38]}, {"text": "czysta", "timestamp": [15.92, 16.36]}, {"text": "niby", "timestamp": [16.48, 16.68]}, {"text": "b\u0142\u0119ki", "timestamp": [16.82, 17.32]}, {"text": "t", "timestamp": [17.4, 17.42]}, {"text": "nieba", "timestamp": [17.5, 17.8]}, {"text": "m\u0105dra", "timestamp": [18.48, 18.9]}, {"text": "zacna", "timestamp": [19.52, 19.94]}, {"text": "mi\u0142a", "timestamp": [20.3, 20.62]}, {"text": "\u0142adna", "timestamp": [21.16, 21.58]}, {"text": "ale", "timestamp": [22.5, 22.64]}, {"text": "czasem", "timestamp": [22.8, 23.2]}, {"text": "przyzna\u0107", "timestamp": [23.38, 23.96]}, {"text": "trzeba", "timestamp": [24.12, 24.5]}, {"text": "\u017ce", "timestamp": [25.16, 25.24]}, {"text": "ten", "timestamp": [25.28, 25.36]}, {"text": "j\u0119zyk", "timestamp": [25.42, 25.74]}, {"text": "najobfitszy", "timestamp": [25.8, 26.58]}, {"text": "w", "timestamp": [26.68, 26.72]}, {"text": "poetyczne", "timestamp": [26.82, 27.52]}, {"text": "r\u00f3\u017cne", "timestamp": [27.6, 27.88]}, {"text": "kwiatki", "timestamp": [27.96, 28.4]}, {"text": "w", "timestamp": [28.94, 28.96]}, {"text": "uczu\u0107", "timestamp": [29.22, 29.62]}, {"text": "sferze", "timestamp": [29.74, 30.14]}, {"text": "pospoliczej", "timestamp": [30.24, 31.0]}, {"text": "zdradza", "timestamp": [31.48, 31.88]}, {"text": "dziwne", "timestamp": [32.02, 32.5]}, {"text": "niedostatki", "timestamp": [32.6, 33.4]}, {"text": "\u017ce", "timestamp": [34.04, 34.16]}, {"text": "w", "timestamp": [34.24, 34.26]}, {"text": "podniebnej", "timestamp": [34.34, 34.82]}, {"text": "wysoko\u015bci", "timestamp": [34.88, 35.56]}, {"text": "nazbyt", "timestamp": [36.02, 36.34]}, {"text": "g\u00f3rnie", "timestamp": [36.4, 36.78]}, {"text": "toczy", "timestamp": [36.88, 37.08]}, {"text": "skrzyd\u0142a", "timestamp": [37.16, 37.66]}, {"text": "a", "timestamp": [38.18, 38.2]}, {"text": "nas", "timestamp": [38.28, 38.58]}, {"text": "ludzi", "timestamp": [39.1, 39.34]}, {"text": "z", "timestamp": [39.42, 39.44]}, {"text": "krwi", "timestamp": [39.54, 39.82]}, {"text": "i", "timestamp": [39.94, 39.98]}, {"text": "ko\u015bci", "timestamp": [40.08, 40.52]}, {"text": "poniewiera", "timestamp": [40.94, 41.56]}, {"text": "gorzej", "timestamp": [42.04, 42.32]}, {"text": "byd\u0142ato", "timestamp": [42.44, 44.14]}, {"text": "co", "timestamp": [44.32, 44.4]}, {"text": "ziemi\u0119", "timestamp": [44.5, 44.8]}, {"text": "wrajnamzmienia", "timestamp": [44.9, 45.9]}, {"text": "\u017cycia", "timestamp": [46.44, 46.7]}, {"text": "ca\u0142y", "timestamp": [46.8, 47.04]}, {"text": "wdzi\u0119k", "timestamp": [47.1, 47.46]}, {"text": "stanowi", "timestamp": [47.54, 48.04]}, {"text": "na", "timestamp": [48.58, 48.66]}, {"text": "to", "timestamp": [48.8, 48.88]}, {"text": "nie", "timestamp": [49.52, 49.62]}, {"text": "ma", "timestamp": [49.7, 49.78]}, {"text": "wyra\u017cenia", "timestamp": [49.86, 50.4]}, {"text": "o", "timestamp": [50.84, 50.86]}, {"text": "tym", "timestamp": [50.96, 51.12]}, {"text": "w", "timestamp": [51.36, 51.38]}, {"text": "polsce", "timestamp": [51.46, 51.92]}, {"text": "si\u0119", "timestamp": [51.98, 52.08]}, {"text": "nie", "timestamp": [52.1, 52.2]}, {"text": "m\u00f3wipytam", "timestamp": [52.24, 53.16]}, {"text": "tu", "timestamp": [53.26, 53.34]}, {"text": "obecne", "timestamp": [53.52, 53.9]}, {"text": "panie", "timestamp": [53.98, 54.3]}, {"text": "by", "timestamp": [54.88, 54.96]}, {"text": "od", "timestamp": [55.22, 55.32]}, {"text": "grubszych", "timestamp": [55.42, 55.86]}, {"text": "zacz\u0105\u0107", "timestamp": [55.92, 56.24]}, {"text": "brak\u00f3w", "timestamp": [56.34, 56.82]}, {"text": "jak", "timestamp": [57.22, 57.46]}, {"text": "mam", "timestamp": [57.54, 57.72]}, {"text": "nazwa\u0107", "timestamp": [57.86, 58.32]}, {"text": "obcowanie", "timestamp": [58.86, 59.76]}, {"text": "dwojga", "timestamp": [60.38, 60.84]}, {"text": "r\u00f3\u017cnej", "timestamp": [61.18, 61.72]}, {"text": "p\u0142ci", "timestamp": [61.9, 62.3]}, {"text": "polak\u00f3w", "timestamp": [62.44, 63.02]}, {"text": "czy", "timestamp": [63.54, 63.68]}, {"text": "du\u017c", "timestamp": [63.94, 64.12]}, {"text": "bratnich", "timestamp": [64.2, 64.56]}, {"text": "pokrewie\u0144stwem", "timestamp": [64.6, 65.36]}, {"text": "czy", "timestamp": [65.82, 65.94]}, {"text": "tarzaniem", "timestamp": [66.3, 66.66]}, {"text": "si\u0119", "timestamp": [66.72, 66.8]}, {"text": "w", "timestamp": [66.84, 66.86]}, {"text": "rozpu\u015bcie", "timestamp": [66.88, 67.5]}, {"text": "serckomuni\u0105", "timestamp": [68.48, 69.3]}, {"text": "czy", "timestamp": [69.52, 69.6]}, {"text": "te\u017c", "timestamp": [69.66, 69.82]}, {"text": "\u015bwi\u0144stwem", "timestamp": [70.12, 70.72]}, {"text": "lub", "timestamp": [71.44, 71.64]}, {"text": "czym", "timestamp": [71.82, 71.96]}, {"text": "innym", "timestamp": [72.1, 72.48]}, {"text": "w", "timestamp": [72.58, 72.6]}, {"text": "takim", "timestamp": [72.64, 72.88]}, {"text": "gu\u015bcie", "timestamp": [72.96, 73.34]}, {"text": "cudzo\u0142o\u017cy\u0107", "timestamp": [74.24, 74.94]}, {"text": "jawno", "timestamp": [75.54, 75.84]}, {"text": "grzeszy\u0107", "timestamp": [75.92, 76.42]}, {"text": "dalej", "timestamp": [76.92, 77.12]}, {"text": "ju\u017c", "timestamp": [77.22, 77.38]}, {"text": "po\u0142o\u017ce", "timestamp": [77.46, 77.76]}, {"text": "kreski", "timestamp": [77.84, 78.22]}, {"text": "reszt\u0105", "timestamp": [78.76, 79.06]}, {"text": "mo\u017ce", "timestamp": [79.22, 79.46]}, {"text": "was", "timestamp": [79.52, 79.7]}, {"text": "ucieszy\u0107", "timestamp": [79.88, 80.38]}, {"text": "juzef", "timestamp": [80.66, 80.96]}, {"text": "albin", "timestamp": [81.1, 81.5]}, {"text": "hrybaczewskicho\u0107", "timestamp": [81.58, 82.92]}, {"text": "poezi", "timestamp": [83.12, 83.82]}, {"text": "\u015bwi\u0119ci", "timestamp": [83.96, 84.44]}, {"text": "wiosne", "timestamp": [84.48, 84.94]}, {"text": "wieszcz\u00f3w", "timestamp": [85.36, 85.96]}, {"text": "naszych", "timestamp": [86.1, 86.42]}, {"text": "dzielna", "timestamp": [86.48, 86.86]}, {"text": "tr\u00f3jka", "timestamp": [86.98, 87.46]}, {"text": "polskie", "timestamp": [88.02, 88.5]}, {"text": "s\u0142ownictwo", "timestamp": [88.6, 89.34]}, {"text": "mi\u0142osne", "timestamp": [89.38, 89.92]}, {"text": "przypomina", "timestamp": [90.32, 90.92]}, {"text": "ksi\u0119dza", "timestamp": [91.4, 91.84]}, {"text": "w\u00f3jkadowody", "timestamp": [91.94, 93.62]}, {"text": "najoczywistsze", "timestamp": [93.74, 94.82]}, {"text": "znajdziesz", "timestamp": [95.24, 95.64]}, {"text": "cho\u0107by", "timestamp": [95.68, 95.98]}, {"text": "w", "timestamp": [96.04, 96.08]}, {"text": "takim", "timestamp": [96.14, 96.36]}, {"text": "g\u0142upstwie", "timestamp": [96.48, 97.02]}, {"text": "\u017ce", "timestamp": [97.46, 97.56]}, {"text": "polskiego", "timestamp": [97.68, 98.24]}, {"text": "s\u0142owa", "timestamp": [98.32, 98.68]}, {"text": "mistrze", "timestamp": [98.78, 99.3]}, {"text": "\u015bni\u0105", "timestamp": [99.72, 99.92]}, {"text": "o", "timestamp": [100.44, 100.46]}, {"text": "rui", "timestamp": [100.68, 101.04]}, {"text": "i", "timestamp": [101.54, 101.58]}, {"text": "por\u00f3bstwie", "timestamp": [101.82, 102.58]}, {"text": "w", "timestamp": [103.08, 103.1]}, {"text": "archaicznym", "timestamp": [103.22, 103.92]}, {"text": "tym", "timestamp": [103.98, 104.1]}, {"text": "zamencie", "timestamp": [104.16, 104.64]}, {"text": "jak", "timestamp": [105.08, 105.2]}, {"text": "ma", "timestamp": [105.24, 105.32]}, {"text": "kwitn\u0105\u0107", "timestamp": [105.38, 105.96]}, {"text": "szcz\u0119\u015bcia", "timestamp": [106.1, 106.66]}, {"text": "era", "timestamp": [106.82, 107.06]}, {"text": "gdzie", "timestamp": [107.58, 107.78]}, {"text": "zatraca", "timestamp": [107.94, 108.48]}, {"text": "si\u0119", "timestamp": [108.58, 108.68]}, {"text": "poj\u0119cie", "timestamp": [108.78, 109.38]}, {"text": "tam", "timestamp": [109.92, 110.08]}, {"text": "i", "timestamp": [110.26, 110.28]}, {"text": "sama", "timestamp": [110.4, 110.66]}, {"text": "rzecz", "timestamp": [110.76, 111.04]}, {"text": "umieraludziom", "timestamp": [111.18, 112.94]}, {"text": "trzeba", "timestamp": [113.08, 113.42]}, {"text": "tak", "timestamp": [113.56, 113.76]}, {"text": "niewiele", "timestamp": [113.84, 114.32]}, {"text": "by", "timestamp": [114.74, 114.8]}, {"text": "na", "timestamp": [114.86, 114.94]}, {"text": "ziemi", "timestamp": [115.06, 115.36]}, {"text": "niebo", "timestamp": [115.48, 115.76]}, {"text": "stworzy\u0107", "timestamp": [115.86, 116.42]}, {"text": "lecz", "timestamp": [116.96, 117.16]}, {"text": "wykrztusi\u0107", "timestamp": [117.4, 118.02]}, {"text": "jak", "timestamp": [118.14, 118.36]}, {"text": "aniele", "timestamp": [118.86, 119.34]}, {"text": "ja", "timestamp": [120.0, 120.06]}, {"text": "chce", "timestamp": [120.1, 120.3]}, {"text": "z", "timestamp": [120.36, 120.38]}, {"text": "tob\u0105", "timestamp": [120.44, 120.7]}, {"text": "cudzo\u0142o\u017cy\u0107", "timestamp": [121.62, 122.46]}, {"text": "jak", "timestamp": [123.22, 123.34]}, {"text": "wyszepta\u0107", "timestamp": [123.38, 123.82]}, {"text": "do", "timestamp": [123.9, 123.96]}, {"text": "dziewcz\u0119cia", "timestamp": [123.98, 124.5]}, {"text": "chc\u0119", "timestamp": [124.78, 125.0]}, {"text": "pozbawi\u0107", "timestamp": [125.46, 126.02]}, {"text": "ci\u0119", "timestamp": [126.14, 126.22]}, {"text": "dziewictwa", "timestamp": [126.24, 126.82]}, {"text": "nie", "timestamp": [127.44, 127.54]}, {"text": "obawiaj", "timestamp": [127.58, 127.88]}, {"text": "si\u0119", "timestamp": [127.96, 128.06]}, {"text": "pocz\u0119cia", "timestamp": [128.38, 129.02]}, {"text": "kpij", "timestamp": [129.48, 129.72]}, {"text": "sobie", "timestamp": [129.8, 130.08]}, {"text": "z", "timestamp": [130.38, 130.4]}, {"text": "jawnogrzesznictwa", "timestamp": [130.5, 132.0]}, {"text": "jak", "timestamp": [132.72, 132.94]}, {"text": "kusi\u0107", "timestamp": [133.12, 133.62]}, {"text": "g\u0142osem", "timestamp": [133.76, 134.2]}, {"text": "zdradzieckim", "timestamp": [134.32, 135.0]}, {"text": "wabi\u0107", "timestamp": [135.46, 135.8]}, {"text": "s\u0142odkich", "timestamp": [135.96, 136.5]}, {"text": "zakl\u0119\u0107", "timestamp": [136.58, 137.08]}, {"text": "gam\u0105", "timestamp": [137.16, 137.46]}, {"text": "ka\u017cdy", "timestamp": [138.0, 138.4]}, {"text": "wyraz", "timestamp": [138.5, 138.84]}, {"text": "pachnie", "timestamp": [138.96, 139.28]}, {"text": "dzieckiem", "timestamp": [139.3, 139.72]}, {"text": "ka\u017cde", "timestamp": [140.12, 140.48]}, {"text": "s\u0142owo", "timestamp": [140.56, 140.94]}, {"text": "drzesie", "timestamp": [141.02, 141.4]}, {"text": "mamo", "timestamp": [141.56, 142.0]}, {"text": "nazbyt", "timestamp": [142.48, 142.88]}, {"text": "trudno", "timestamp": [143.02, 143.44]}, {"text": "w", "timestamp": [143.52, 143.54]}, {"text": "tym", "timestamp": [143.6, 143.74]}, {"text": "dialekcie", "timestamp": [143.86, 144.38]}, {"text": "romansowe", "timestamp": [144.82, 145.36]}, {"text": "snu\u0107", "timestamp": [145.46, 145.74]}, {"text": "intrygi", "timestamp": [145.88, 146.4]}, {"text": "polak", "timestamp": [146.98, 147.3]}, {"text": "cnote", "timestamp": [147.48, 147.9]}, {"text": "ma", "timestamp": [147.98, 148.04]}, {"text": "w", "timestamp": [148.16, 148.18]}, {"text": "respekcie", "timestamp": [148.22, 148.88]}, {"text": "lub", "timestamp": [149.22, 149.4]}, {"text": "tentuje", "timestamp": [149.78, 150.32]}, {"text": "j\u0105", "timestamp": [150.44, 150.52]}, {"text": "na", "timestamp": [151.14, 151.24]}, {"text": "migi", "timestamp": [151.32, 151.64]}, {"text": "st\u0105d", "timestamp": [152.5, 152.92]}, {"text": "gdy", "timestamp": [153.2, 153.32]}, {"text": "w", "timestamp": [153.36, 153.38]}, {"text": "polsce", "timestamp": [153.44, 153.88]}, {"text": "do", "timestamp": [153.96, 154.02]}, {"text": "kolacji", "timestamp": [154.08, 154.6]}, {"text": "p\u0142cie", "timestamp": [154.94, 155.26]}, {"text": "odmienne", "timestamp": [155.36, 155.88]}, {"text": "si\u0105d\u0105", "timestamp": [155.98, 156.32]}, {"text": "spo\u0142em", "timestamp": [156.48, 156.92]}, {"text": "g\u0142\u00f3wna", "timestamp": [157.44, 157.86]}, {"text": "cz\u0105stka", "timestamp": [157.96, 158.38]}, {"text": "konwersacji", "timestamp": [158.44, 159.2]}, {"text": "zwyk\u0142a", "timestamp": [159.5, 159.8]}, {"text": "toczy\u0107", "timestamp": [159.9, 160.22]}, {"text": "si\u0119", "timestamp": [160.3, 160.42]}, {"text": "pod", "timestamp": [161.12, 161.26]}, {"text": "sto\u0142em", "timestamp": [161.34, 161.72]}, {"text": "niech", "timestamp": [162.42, 162.58]}, {"text": "upadnie", "timestamp": [162.66, 162.98]}, {"text": "ci", "timestamp": [163.04, 163.1]}, {"text": "serweta", "timestamp": [163.16, 163.62]}, {"text": "cz\u0142owiek", "timestamp": [164.16, 164.52]}, {"text": "oczom", "timestamp": [164.68, 164.94]}, {"text": "swym", "timestamp": [165.04, 165.26]}, {"text": "nie", "timestamp": [165.34, 165.42]}, {"text": "wierzy", "timestamp": [165.48, 165.78]}, {"text": "gdzie", "timestamp": [166.24, 166.42]}, {"text": "m\u0119\u017cczyzna", "timestamp": [166.46, 167.14]}, {"text": "gdzie", "timestamp": [167.44, 167.6]}, {"text": "kobieta", "timestamp": [167.64, 168.02]}, {"text": "kt\u00f3ranoga", "timestamp": [168.44, 169.32]}, {"text": "gdzie", "timestamp": [169.4, 169.6]}, {"text": "nale\u017cy", "timestamp": [169.68, 170.12]}, {"text": "pantofelk\u00f3w", "timestamp": [170.64, 171.54]}, {"text": "but\u00f3w", "timestamp": [171.8, 172.22]}, {"text": "g\u0119stwa", "timestamp": [172.28, 172.78]}, {"text": "fantastycznie", "timestamp": [173.1, 173.9]}, {"text": "popl\u0105tana", "timestamp": [173.94, 174.6]}, {"text": "stacza", "timestamp": [175.02, 175.32]}, {"text": "walki", "timestamp": [175.42, 175.9]}, {"text": "pe\u0142ne", "timestamp": [176.06, 176.42]}, {"text": "m\u0119stwa", "timestamp": [176.48, 177.0]}, {"text": "istny", "timestamp": [177.4, 177.82]}, {"text": "grunwald", "timestamp": [177.92, 178.64]}, {"text": "mistrza", "timestamp": [178.76, 179.24]}, {"text": "jana", "timestamp": [179.32, 179.66]}, {"text": "tak", "timestamp": [180.14, 180.34]}, {"text": "pod", "timestamp": [180.46, 180.6]}, {"text": "sto\u0142em", "timestamp": [180.66, 181.08]}, {"text": "wiecz\u00f3r", "timestamp": [181.22, 181.58]}, {"text": "ca\u0142y", "timestamp": [181.76, 182.06]}, {"text": "gimnastyczne", "timestamp": [182.5, 183.3]}, {"text": "trwa", "timestamp": [183.4, 183.68]}, {"text": "\u0107wiczenie", "timestamp": [183.8, 184.32]}, {"text": "na", "timestamp": [184.64, 184.7]}, {"text": "przy", "timestamp": [184.76, 184.86]}, {"text": "stole", "timestamp": [184.94, 185.28]}, {"text": "komuna\u0142y", "timestamp": [185.68, 186.38]}, {"text": "o\u017ce", "timestamp": [186.68, 186.9]}, {"text": "romskim", "timestamp": [186.98, 187.64]}, {"text": "lub", "timestamp": [187.82, 188.04]}, {"text": "ipsenie", "timestamp": [188.28, 188.84]}, {"text": "lecz", "timestamp": [189.42, 189.62]}, {"text": "najci\u0119\u017csz\u0105", "timestamp": [189.88, 190.68]}, {"text": "budzi", "timestamp": [190.88, 191.12]}, {"text": "troske", "timestamp": [191.2, 191.64]}, {"text": "\u017ce", "timestamp": [192.06, 192.14]}, {"text": "marnieje", "timestamp": [192.22, 192.8]}, {"text": "lud", "timestamp": [193.0, 193.2]}, {"text": "nasz", "timestamp": [193.32, 193.52]}, {"text": "chwacki", "timestamp": [193.58, 194.1]}, {"text": "\u017ce", "timestamp": [194.56, 194.64]}, {"text": "ju\u017c", "timestamp": [194.68, 194.86]}, {"text": "cich\u0105", "timestamp": [195.1, 195.5]}, {"text": "polsk\u0105", "timestamp": [195.8, 196.26]}, {"text": "wiosk\u0119", "timestamp": [196.42, 196.88]}, {"text": "skazi\u0142", "timestamp": [197.36, 197.74]}, {"text": "\u017cargon", "timestamp": [197.86, 198.42]}, {"text": "literackinawie\u015b", "timestamp": [198.72, 200.74]}, {"text": "gdy", "timestamp": [201.16, 201.3]}, {"text": "si\u0119", "timestamp": [201.36, 201.44]}, {"text": "cz\u0142ek", "timestamp": [201.54, 201.78]}, {"text": "dob\u0119dzie", "timestamp": [201.84, 202.32]}, {"text": "chc\u0105c", "timestamp": [202.7, 203.06]}, {"text": "odetchn\u0105\u0107", "timestamp": [203.28, 203.9]}, {"text": "\u017cyciem", "timestamp": [204.04, 204.3]}, {"text": "zdrowszem", "timestamp": [204.4, 204.92]}, {"text": "s\u0142yszy", "timestamp": [205.24, 205.58]}, {"text": "ka\u015bka", "timestamp": [206.16, 206.54]}, {"text": "jak", "timestamp": [207.02, 207.22]}, {"text": "ze", "timestamp": [207.28, 207.38]}, {"text": "b\u0119dzie", "timestamp": [207.44, 207.84]}, {"text": "wzgl\u0119dem", "timestamp": [208.16, 208.62]}, {"text": "tego", "timestamp": [208.72, 209.0]}, {"text": "co", "timestamp": [209.18, 209.28]}, {"text": "i", "timestamp": [209.38, 209.44]}, {"text": "owszem", "timestamp": [209.6, 210.0]}, {"text": "widz\u0119", "timestamp": [210.68, 210.9]}, {"text": "tu", "timestamp": [211.02, 211.1]}, {"text": "zebran\u0105", "timestamp": [211.2, 211.68]}, {"text": "t\u0142umnie", "timestamp": [211.84, 212.3]}, {"text": "kap\u0142an\u00f3w", "timestamp": [212.78, 213.46]}, {"text": "sztuki", "timestamp": [213.54, 213.9]}, {"text": "elite", "timestamp": [214.06, 214.48]}, {"text": "co", "timestamp": [215.0, 215.08]}, {"text": "swe", "timestamp": [215.14, 215.26]}, {"text": "kud\u0142y", "timestamp": [215.36, 215.74]}, {"text": "wznosz\u0105", "timestamp": [215.82, 216.16]}, {"text": "dumnie", "timestamp": [216.32, 216.76]}, {"text": "ponad", "timestamp": [216.96, 217.28]}, {"text": "rzesze", "timestamp": [217.4, 217.72]}, {"text": "pospolite", "timestamp": [217.84, 218.52]}, {"text": "wy", "timestamp": [219.22, 219.32]}, {"text": "\u015bwietlanych", "timestamp": [220.0, 220.52]}, {"text": "duch\u00f3w", "timestamp": [220.62, 220.92]}, {"text": "zwi\u0105zek", "timestamp": [220.98, 221.56]}, {"text": "w", "timestamp": [222.0, 222.04]}, {"text": "idei", "timestamp": [222.4, 223.0]}, {"text": "stru\u017ceczystej", "timestamp": [223.14, 224.16]}, {"text": "wasz", "timestamp": [224.8, 225.1]}, {"text": "to", "timestamp": [225.18, 225.26]}, {"text": "jest", "timestamp": [225.32, 225.58]}, {"text": "psi", "timestamp": [225.82, 226.12]}, {"text": "obowi\u0105zek", "timestamp": [226.4, 227.16]}, {"text": "kszta\u0142ci\u0107", "timestamp": [227.52, 228.0]}, {"text": "j\u0119zyk", "timestamp": [228.12, 228.56]}, {"text": "ten", "timestamp": [228.6, 228.74]}, {"text": "ojczysty", "timestamp": [228.86, 229.42]}, {"text": "sko\u0144czcie", "timestamp": [229.8, 230.3]}, {"text": "wasze", "timestamp": [230.4, 230.64]}, {"text": "komedyje", "timestamp": [230.72, 231.2]}, {"text": "schowajcie", "timestamp": [231.74, 232.16]}, {"text": "pawie", "timestamp": [232.22, 232.44]}, {"text": "ogony", "timestamp": [232.54, 232.9]}, {"text": "\u017cyjcie", "timestamp": [233.38, 233.8]}, {"text": "czym", "timestamp": [234.16, 234.32]}, {"text": "ka\u017cdy", "timestamp": [234.44, 234.9]}, {"text": "z", "timestamp": [235.0, 235.02]}, {"text": "nas", "timestamp": [235.1, 235.3]}, {"text": "\u017cyje", "timestamp": [235.62, 235.92]}, {"text": "id\u017acie", "timestamp": [236.4, 236.78]}, {"text": "kocha\u0107", "timestamp": [237.64, 238.1]}, {"text": "zamiliony", "timestamp": [239.2, 239.84]}, {"text": "do\u015b\u0107", "timestamp": [240.82, 241.22]}, {"text": "nastroj\u00f3w", "timestamp": [241.44, 242.06]}, {"text": "waszych", "timestamp": [242.18, 242.54]}, {"text": "dranie", "timestamp": [242.8, 243.24]}, {"text": "uczcie", "timestamp": [243.68, 244.0]}, {"text": "m\u00f3wi\u0107", "timestamp": [244.16, 244.78]}, {"text": "waszych", "timestamp": [245.04, 245.32]}, {"text": "braci", "timestamp": [245.4, 245.8]}, {"text": "to", "timestamp": [246.24, 246.34]}, {"text": "jest", "timestamp": [246.46, 246.66]}, {"text": "wasze", "timestamp": [246.74, 247.0]}, {"text": "powo\u0142anie", "timestamp": [247.16, 247.84]}, {"text": "od", "timestamp": [248.28, 248.4]}, {"text": "tego", "timestamp": [248.54, 248.9]}, {"text": "was", "timestamp": [249.3, 249.52]}, {"text": "nar\u00f3d", "timestamp": [249.68, 250.06]}, {"text": "p\u0142aci", "timestamp": [250.22, 250.7]}, {"text": "j\u0119zyk", "timestamp": [251.42, 251.98]}, {"text": "naszym", "timestamp": [252.1, 252.34]}, {"text": "skarbem", "timestamp": [252.42, 252.9]}, {"text": "\u015bwi\u0119tym", "timestamp": [253.0, 253.52]}, {"text": "niej", "timestamp": [253.96, 254.12]}, {"text": "graszk\u0105", "timestamp": [254.22, 254.66]}, {"text": "oboj\u0119tn\u0105", "timestamp": [254.78, 255.36]}, {"text": "nie", "timestamp": [255.82, 255.88]}, {"text": "krwi\u0105", "timestamp": [255.96, 256.22]}, {"text": "ale", "timestamp": [256.7, 256.88]}, {"text": "atramentem", "timestamp": [257.1, 257.92]}, {"text": "bije", "timestamp": [258.4, 258.68]}, {"text": "dzisiaj", "timestamp": [258.76, 259.16]}, {"text": "lud\u00f3w", "timestamp": [259.32, 259.62]}, {"text": "t\u0119tnomusi", "timestamp": [259.74, 261.14]}, {"text": "naprz\u00f3d", "timestamp": [261.26, 261.84]}, {"text": "i\u015b\u0107", "timestamp": [262.0, 262.34]}, {"text": "z", "timestamp": [262.56, 262.58]}, {"text": "\u017cywemi", "timestamp": [262.66, 263.12]}, {"text": "a", "timestamp": [263.78, 263.82]}, {"text": "nie", "timestamp": [263.86, 263.96]}, {"text": "t\u0119pi\u0107", "timestamp": [264.08, 264.54]}, {"text": "\u017cycia", "timestamp": [264.78, 265.06]}, {"text": "zarut", "timestamp": [265.12, 265.56]}, {"text": "sok\u00f3w", "timestamp": [266.18, 266.6]}, {"text": "pe\u0142nie", "timestamp": [266.74, 267.08]}, {"text": "czerpa\u0107", "timestamp": [267.2, 267.64]}, {"text": "z", "timestamp": [267.8, 267.84]}, {"text": "ziemi", "timestamp": [267.94, 268.24]}, {"text": "jaki", "timestamp": [268.94, 269.16]}, {"text": "j\u0119zyk", "timestamp": [269.24, 269.76]}, {"text": "taki", "timestamp": [270.1, 270.4]}, {"text": "nar\u00f3d", "timestamp": [270.52, 271.0]}, {"text": "pisane", "timestamp": [271.72, 272.04]}, {"text": "w", "timestamp": [272.08, 272.1]}, {"text": "roku", "timestamp": [272.16, 272.38]}, {"text": "tysi\u0105c", "timestamp": [272.46, 272.76]}, {"text": "dziewi\u0119\u0107set", "timestamp": [272.82, 273.34]}, {"text": "si\u00f3dmym", "timestamp": [273.42, 273.78]}]}